OctopusAgile
