Metadata-Version: 2.1
Name: OctopusAgile
Version: 0.0.6
Summary: A library to interface with the Octopus Agile API
Home-page: https://github.com/markgdev/OctopusAgile
Author: Mark G
Author-email: 
License: apache-2.0
Download-URL: https://github.com/markgdev/OctopusAgile/archive/v0.0.6.tar.gz
Keywords: Octopus,Agile
Platform: UNKNOWN
Classifier: Development Status :: 3 - Alpha
Classifier: Intended Audience :: Developers
Classifier: Topic :: Software Development :: Build Tools
Classifier: License :: OSI Approved :: Apache Software License
Classifier: Programming Language :: Python :: 3
Classifier: Programming Language :: Python :: 3.4
Classifier: Programming Language :: Python :: 3.5
Classifier: Programming Language :: Python :: 3.6
